LICENSE
MANIFEST.in
README.md
setup.py
adobo/IO.py
adobo/VERSION
adobo/__init__.py
adobo/_colors.py
adobo/_constants.py
adobo/_log.py
adobo/_stats.py
adobo/bio.py
adobo/bulk.py
adobo/clustering.py
adobo/data.py
adobo/de.py
adobo/dr.py
adobo/hvg.py
adobo/normalize.py
adobo/plotting.py
adobo/preproc.py
adobo/traj.py
adobo.egg-info/PKG-INFO
adobo.egg-info/SOURCES.txt
adobo.egg-info/dependency_links.txt
adobo.egg-info/requires.txt
adobo.egg-info/top_level.txt
adobo/data/GO_0007049.txt
adobo/data/GSE95315.tab.gz
adobo/data/GSM3687214_countTable_K11_choroidPlexus_wt.txt.gz
adobo/data/g2m_genes.txt
adobo/data/human.gencode_v32.genes.txt
adobo/data/markers.tsv
adobo/data/mouse.gencode_v23.genes.txt
adobo/data/mouse_gene_symbols.txt
adobo/data/pbmc8k.mat.gz
adobo/data/rRNA_genes.txt
adobo/data/s_genes.txt
adobo/glm/README.md
adobo/glm/__init__.py
adobo/glm/families.py
adobo/glm/glm.py
adobo/glm/glmnet.py
adobo/glm/simulation.py
adobo/glm/utils.py
adobo/irlbpy/__init__.py
adobo/irlbpy/irlb.py
adobo/libs/pdf.c
notebooks/choroidPlexus.ipynb
notebooks/pbmc8k.ipynb