Metadata-Version: 1.0
Name: adobo
Version: 0.2.57
Summary: An analysis framework for single cell gene expression data.
Home-page: https://github.com/oscar-franzen/adobo
Author: Oscar Franzén
Author-email: p.oscar.franzen@gmail.com
License: LICENSE
Platform: UNKNOWN
